automation9
