Metadata-Version: 1.1
Name: automation9
Version: 0.0.15
Summary: An automation library
Home-page: https://github.com/nikoladang/automation9
Author: Nikola Dang
Author-email: ducthinhdt@gmail.com
License: UNKNOWN
Download-URL: https://github.com/nikoladang/automation9/tarball/0.1
Keywords: testing,logging,example,automation,signing
Platform: UNKNOWN
Classifier: Development Status :: 5 - Production/Stable
Classifier: Intended Audience :: Developers
Classifier: Natural Language :: English
Classifier: License :: OSI Approved :: MIT License
Classifier: Operating System :: OS Independent
Classifier: Programming Language :: Python
Classifier: Programming Language :: Python :: 2
Classifier: Programming Language :: Python :: 2.6
Classifier: Programming Language :: Python :: 2.7
Classifier: Programming Language :: Python :: 3
Classifier: Programming Language :: Python :: 3.3
Classifier: Programming Language :: Python :: 3.4
Classifier: Programming Language :: Python :: 3.5
Classifier: Programming Language :: Python :: Implementation :: CPython
Classifier: Programming Language :: Python :: Implementation :: PyPy
Classifier: Topic :: Software Development :: Libraries :: Python Modules
